blast_embedding/__init__.py
blast_embedding/algorithm/__init__.py
blast_embedding/algorithm/embedding_blast.py
blast_embedding/algorithm/refined_embedding_blast.py
blast_embedding/benchmarking/__init__.py
blast_embedding/benchmarking/blast_comparison.py
blast_embedding/embedding/__init__.py
blast_embedding/embedding/sequence_embeddings.py
blast_embedding-0.1.0.dist-info/METADATA
blast_embedding-0.1.0.dist-info/WHEEL
blast_embedding-0.1.0.dist-info/top_level.txt
blast_embedding-0.1.0.dist-info/RECORD
